surquest/GCP/tracer/__init__.py
surquest/GCP/tracer/tracer.py
surquest_gcp_tracer-0.1.0.dist-info/METADATA
surquest_gcp_tracer-0.1.0.dist-info/WHEEL
surquest_gcp_tracer-0.1.0.dist-info/licenses/LICENSE
surquest_gcp_tracer-0.1.0.dist-info/RECORD
