Metadata-Version: 2.1
Name: surquest-GCP-tracer
Version: 0.1.0
Summary: Wrapper around Google Cloud Platform (GCP) tracing library
Project-URL: Homepage, https://github.com/surquest/python-gcp-tracer
Project-URL: Bug Tracker, https://github.com/surquest/python-gcp-tracer/issues
Author-email: Michal Švarc <michal.svarc@surquest.com>
License-File: LICENSE
Requires-Dist: google-auth<3.0.0,>=2.10.0
Requires-Dist: opentelemetry-exporter-gcp-trace~=1.4.0
Requires-Dist: starlette>=0.24.0
Provides-Extra: test
Requires-Dist: pytest-cov>=4.0.0; extra == 'test'
Requires-Dist: pytest>=7.2.1; extra == 'test'
